munpyy/__init__.py
munpyy-0.0.1.dist-info/licenses/LICENSE
munpyy-0.0.1.dist-info/METADATA
munpyy-0.0.1.dist-info/WHEEL
munpyy-0.0.1.dist-info/top_level.txt
munpyy-0.0.1.dist-info/RECORD
